README.txt
setup.py
twitsilver/__init__.py
twitsilver/growl.py
twitsilver/install.py
twitsilver/keychain.py
twitsilver/tweet.py
twitsilver.egg-info/PKG-INFO
twitsilver.egg-info/SOURCES.txt
twitsilver.egg-info/dependency_links.txt
twitsilver.egg-info/entry_points.txt
twitsilver.egg-info/not-zip-safe
twitsilver.egg-info/requires.txt
twitsilver.egg-info/top_level.txt