Metadata-Version: 1.0
Name: twitsilver
Version: 0.2
Summary: A Quicksilver client for twitter
Home-page: http://github.com/tomster/twitsilver/
Author: Tom Lazar
Author-email: tom@tomster.org
License: BSD
Keywords: Quicksilver twitter OSX
Platform: UNKNOWN
Classifier: Development Status :: 5 - Production/Stable
Classifier: Environment :: MacOS X
Classifier: Operating System :: MacOS :: MacOS X
Classifier: Intended Audience :: End Users/Desktop
Classifier: License :: OSI Approved :: BSD License
Classifier: Topic :: Communications
